README.md
setup.py
balegramx/__init__.py
balegramx/client.py
balegramx/types.py
balegramx.egg-info/PKG-INFO
balegramx.egg-info/SOURCES.txt
balegramx.egg-info/dependency_links.txt
balegramx.egg-info/requires.txt
balegramx.egg-info/top_level.txt
balegramx/network/connection.py
balegramx/objects/objs.py