Metadata-Version: 2.1
Name: balegramx
Version: 2.0.1
Summary: Bale Messenger Async/Sync Client Library
Home-page: https://github.com/AshyX-Dev/balegram
Author: Host1let
Author-email: sqlmapssh@gmail.com
License: MIT
Download-URL: https://github.com/AshyX-Dev/balegram/archive/refs/heads/main.zip
Keywords: balegram,Balegram,blgram
Platform: UNKNOWN
Classifier: Development Status :: 3 - Alpha
Classifier: Intended Audience :: Developers
Classifier: Topic :: Software Development :: Build Tools
Classifier: License :: OSI Approved :: MIT License
Classifier: Programming Language :: Python :: 3
Classifier: Programming Language :: Python :: 3.8
Classifier: Programming Language :: Python :: 3.9
Classifier: Programming Language :: Python :: 3.10
Classifier: Programming Language :: Python :: 3.11
Classifier: Programming Language :: Python :: 3.12
